pyo3_branchwater-0.4.1.dist-info/METADATA
pyo3_branchwater-0.4.1.dist-info/WHEEL
pyo3_branchwater-0.4.1.dist-info/entry_points.txt
pyo3_branchwater/__init__.py
pyo3_branchwater/sourmash_plugin.py
pyo3_branchwater/__main__.py
pyo3_branchwater/pyo3_branchwater.cpython-38-darwin.so
pyo3_branchwater-0.4.1.dist-info/RECORD
