Metadata-Version: 2.1
Name: pyo3-branchwater
Version: 0.4.1
Classifier: Programming Language :: Rust
Classifier: Programming Language :: Python :: Implementation :: CPython
Classifier: Programming Language :: Python :: Implementation :: PyPy
Summary: fast search and gather extensions for sourmash
Requires-Python: >=3.8
